memrise/__init__.py
memrise/__main__.py
memrise/data/__init__.py
memrise/data/constant.py
memrise/data/data.py
memrise/extract/__init__.py
memrise/extract/const.py
memrise/extract/extract.py
memrise/memrise.py
memrise/translator/__init__.py
memrise/translator/translator.py
memrise-1.3.1.dist-info/LICENSE
memrise-1.3.1.dist-info/WHEEL
memrise-1.3.1.dist-info/METADATA
memrise-1.3.1.dist-info/RECORD
