Metadata-Version: 2.1
Name: memrise
Version: 1.3.1
Summary: Scraping the vocabulary from the Memrise course
Home-page: https://github.com/tquangsdh20/memrise
License: MIT
Author: Joseph Quang
Author-email: tquangsdh20@hcmut.edu.vn
Requires-Python: >=3.6,<4.0
Classifier: Development Status :: 5 - Production/Stable
Classifier: Intended Audience :: Education
Classifier: Intended Audience :: End Users/Desktop
Classifier: License :: OSI Approved :: MIT License
Classifier: Operating System :: OS Independent
Classifier: Programming Language :: Python :: 3
Classifier: Programming Language :: Python :: 3.10
Classifier: Programming Language :: Python :: 3.6
Classifier: Programming Language :: Python :: 3.7
Classifier: Programming Language :: Python :: 3.8
Classifier: Programming Language :: Python :: 3.9
Project-URL: Repository, https://github.com/tquangsdh20/memrise
